MANIFEST.in
README.rst
setup.py
doc/Makefile
doc/conf.py
doc/index.rst
restricted_pkg/__init__.py
restricted_pkg/base.py
restricted_pkg/commands.py
restricted_pkg/compat.py
restricted_pkg/validators.py
restricted_pkg.egg-info/PKG-INFO
restricted_pkg.egg-info/SOURCES.txt
restricted_pkg.egg-info/dependency_links.txt
restricted_pkg.egg-info/entry_points.txt
restricted_pkg.egg-info/top_level.txt
tests/__init__.py
tests/test_base.py
tests/test_command.py