Metadata-Version: 1.1
Name: restricted-pkg
Version: 1.1.2
Summary: A simple setup.py helper for private repositories
Home-page: http://github.com/rbarrois/restricted_pkg
Author: Raphaël Barrois
Author-email: raphael.barrois@polytechnique.org
License: MIT
Download-URL: http://pypi.python.org/pypi/restricted_pkg/
Keywords: pypi,package index,private,repository
Platform: UNKNOWN
Classifier: Development Status :: 5 - Production/Stable
Classifier: Intended Audience :: Developers
Classifier: License :: OSI Approved :: MIT License
Classifier: Topic :: Software Development :: Libraries :: Python Modules
Classifier: Operating System :: OS Independent
Classifier: Programming Language :: Python
Classifier: Programming Language :: Python :: 3
Classifier: Programming Language :: Python :: 2
